vmlab_py-0.1.19.dist-info/METADATA
vmlab_py-0.1.19.dist-info/WHEEL
vmlab_py/__init__.py
vmlab_py/vmlab_py.cpython-312-x86_64-linux-gnu.so
vmlab_py-0.1.19.dist-info/RECORD
