Metadata-Version: 2.4
Name: vmlab_py
Version: 0.1.19
Classifier: Programming Language :: Python
Classifier: Programming Language :: Python :: 3
Classifier: Programming Language :: Rust
Classifier: License :: OSI Approved :: MIT License
Classifier: Operating System :: OS Independent
Summary: A Rust-based library from vmlab
Keywords: rust,mask,pyo3,numpy
Author-email: Jaemin Kim <geminik23@vmonster.io>
License: MIT
